Metadata-Version: 2.1
Name: uniprot-meta-tool
Version: 0.2.1
Summary: retrieves and parses metadata from UniProt.org with simple object-based interface
Home-page: https://github.com/protdb/uniprot_meta_tool
Author: Kirill Nikolsky
Author-email: kirill.s.nikolsky@yandex.ru
Classifier: Programming Language :: Python :: 3.10
Classifier: Operating System :: OS Independent
License-File: LICENSE
Requires-Dist: requests
Requires-Dist: jmespath
